jasudh1/__init__.py
jasudh1/bicode1.py
jasudh1/bicode2.py
jasudh1/bicode3.py
beep_node-0.5.dist-info/METADATA
beep_node-0.5.dist-info/WHEEL
beep_node-0.5.dist-info/top_level.txt
beep_node-0.5.dist-info/RECORD
