Metadata-Version: 2.1
Name: beep_node
Version: 0.5
Summary: Library of converted notebooks
Home-page: UNKNOWN
Author: John Doe
License: UNKNOWN
Platform: UNKNOWN
